email_message_aws_ses_local/__init__.py
email_message_aws_ses_local/email_message.py
email_message_aws_ses_local/ses_email.py
email_message_aws_ses_local-0.0.19.dist-info/METADATA
email_message_aws_ses_local-0.0.19.dist-info/WHEEL
email_message_aws_ses_local-0.0.19.dist-info/top_level.txt
email_message_aws_ses_local-0.0.19.dist-info/RECORD
