Metadata-Version: 2.4
Name: email-message-aws-ses-local
Version: 0.0.19
Summary: PyPI Package for Circles AWS email
Home-page: https://github.com/circles-zone/email-message-aws-ses-local-python-package
Author: Circles
Author-email: info@circlez.ai
Classifier: Programming Language :: Python :: 3
Classifier: Operating System :: OS Independent
Requires-Dist: boto3>=1.28.70
Requires-Dist: logger-local>=0.0.135
Requires-Dist: message-local>=0.0.93
Requires-Dist: python-sdk-remote>=0.0.93
Requires-Dist: database-mysql-local>=0.1.10
Dynamic: author
Dynamic: author-email
Dynamic: classifier
Dynamic: description
Dynamic: description-content-type
Dynamic: home-page
Dynamic: requires-dist
Dynamic: summary
